micropython_pct2075/__init__.py
micropython_pct2075/i2c_helpers.py
micropython_pct2075/pct2075.py
micropython_pct2075-0.1.0.dist-info/LICENSE
micropython_pct2075-0.1.0.dist-info/METADATA
micropython_pct2075-0.1.0.dist-info/WHEEL
micropython_pct2075-0.1.0.dist-info/top_level.txt
micropython_pct2075-0.1.0.dist-info/RECORD
