Metadata-Version: 2.1
Name: micropython-pct2075
Version: 0.1.0
Summary: MciroPython Driver for the NXP Semiconductors Temperature Sensor
Author-email: JDM <xxyx@mailmeto.mozmail.com>
License: MIT
Project-URL: Homepage, https://github.com/jposada202020/MicroPython_PCT2075
Keywords: sensor,micropython,pct2075,temperature,sensor,nxp,driver
Classifier: Intended Audience :: Developers
Classifier: Topic :: Software Development :: Libraries
Classifier: Topic :: Software Development :: Embedded Systems
Classifier: Topic :: System :: Hardware
Classifier: License :: OSI Approved :: MIT License
Classifier: Programming Language :: Python :: Implementation :: MicroPython
License-File: LICENSE
